auditorium/__init__.py
auditorium/__main__.py
auditorium/components.py
auditorium/demo.py
auditorium/markdown.py
auditorium/server.py
auditorium/show.py
auditorium/static/css/auditorium-black.css
auditorium/static/css/auditorium-white.css
auditorium/static/css/auditorium.css
auditorium/static/css/print/paper.css
auditorium/static/css/print/pdf.css
auditorium/static/css/reset.css
auditorium/static/css/reveal.css
auditorium/static/css/server.css
auditorium/static/css/theme/beige.css
auditorium/static/css/theme/black.css
auditorium/static/css/theme/blood.css
auditorium/static/css/theme/league.css
auditorium/static/css/theme/moon.css
auditorium/static/css/theme/night.css
auditorium/static/css/theme/serif.css
auditorium/static/css/theme/simple.css
auditorium/static/css/theme/sky.css
auditorium/static/css/theme/solarized.css
auditorium/static/css/theme/white.css
auditorium/static/img/banner.jpg
auditorium/static/img/favicon.ico
auditorium/static/img/logo.png
auditorium/static/img/logo.svg
auditorium/static/js/auditorium.js
auditorium/static/js/reveal.js
auditorium/static/lib/font/league-gothic/LICENSE
auditorium/static/lib/font/league-gothic/league-gothic.css
auditorium/static/lib/font/league-gothic/league-gothic.eot
auditorium/static/lib/font/league-gothic/league-gothic.ttf
auditorium/static/lib/font/league-gothic/league-gothic.woff
auditorium/static/lib/font/source-sans-pro/LICENSE
auditorium/static/lib/font/source-sans-pro/source-sans-pro-italic.eot
auditorium/static/lib/font/source-sans-pro/source-sans-pro-italic.ttf
auditorium/static/lib/font/source-sans-pro/source-sans-pro-italic.woff
auditorium/static/lib/font/source-sans-pro/source-sans-pro-regular.eot
auditorium/static/lib/font/source-sans-pro/source-sans-pro-regular.ttf
auditorium/static/lib/font/source-sans-pro/source-sans-pro-regular.woff
auditorium/static/lib/font/source-sans-pro/source-sans-pro-semibold.eot
auditorium/static/lib/font/source-sans-pro/source-sans-pro-semibold.ttf
auditorium-20.2.1.dist-info/entry_points.txt
auditorium-20.2.1.dist-info/LICENSE
auditorium-20.2.1.dist-info/WHEEL
auditorium-20.2.1.dist-info/METADATA
auditorium-20.2.1.dist-info/RECORD
