Metadata-Version: 2.1
Name: auditorium
Version: 20.2.1
Summary: A Python-powered slideshow maker with steroids.
License: MIT
Author: Alejandro Piad
Author-email: alepiad@gmail.com
Requires-Python: >=3.6.1,<4.0.0
Classifier: License :: OSI Approved :: MIT License
Classifier: Programming Language :: Python :: 3
Classifier: Programming Language :: Python :: 3.7
Classifier: Programming Language :: Python :: 3.8
Provides-Extra: server
Requires-Dist: aiofiles (>=0.4.0,<0.5.0)
Requires-Dist: fastapi (>=0.45.0,<0.46.0)
Requires-Dist: fire (>=0.2.1,<0.3.0)
Requires-Dist: jinja2 (>=2.10.3,<3.0.0)
Requires-Dist: markdown (>=3.1.1,<4.0.0)
Requires-Dist: pygments (>=2.5.2,<3.0.0)
Requires-Dist: uvicorn (>=0.11.1,<0.12.0); extra == "server"
Requires-Dist: websockets (>=8.1,<9.0)
